trollbot/__init__.py
trollbot/bot.py
trollbot/context.py
trollbot/headers.py
trollbot/user.py
trollbot-1.2.dist-info/LICENSE
trollbot-1.2.dist-info/METADATA
trollbot-1.2.dist-info/WHEEL
trollbot-1.2.dist-info/entry_points.txt
trollbot-1.2.dist-info/RECORD
