Metadata-Version: 2.1
Name: trollbot
Version: 1.2
Summary: A python library dedicated to making bots for Trollbox (and chatrooms alike)
Author: mewhenthe
Author-email: xsare435@gmail.com
Requires-Python: >=3.11,<4.0
Classifier: Programming Language :: Python :: 3
Classifier: Programming Language :: Python :: 3.11
Requires-Dist: python-socketio (==4.6.1)
